Metadata-Version: 1.0
Name: static-response-server
Version: 0.1
Summary: Static response server for REST pocs
Home-page: https://github.com/alexrochas/static-response-server
Author: Alex Rocha
Author-email: alex.rochas@yahoo.com.br
License: MIT
Platform: UNKNOWN
